sigenergy2mqtt/__init__.py
sigenergy2mqtt/__main__.py
sigenergy2mqtt/common/__init__.py
sigenergy2mqtt/common/consumption_method.py
sigenergy2mqtt/common/protocol.py
sigenergy2mqtt/common/register_access.py
sigenergy2mqtt/common/types.py
sigenergy2mqtt/config/__init__.py
sigenergy2mqtt/config/auto_discovery.py
sigenergy2mqtt/config/config.py
sigenergy2mqtt/config/const.py
sigenergy2mqtt/config/home_assistant_config.py
sigenergy2mqtt/config/modbus_config.py
sigenergy2mqtt/config/mqtt_config.py
sigenergy2mqtt/config/pvoutput_config.py
sigenergy2mqtt/config/smart_port_config.py
sigenergy2mqtt/config/validation.py
sigenergy2mqtt/config/version.py
sigenergy2mqtt/devices/__init__.py
sigenergy2mqtt/devices/ac_charger.py
sigenergy2mqtt/devices/dc_charger.py
sigenergy2mqtt/devices/device.py
sigenergy2mqtt/devices/grid_code.py
sigenergy2mqtt/devices/grid_sensor.py
sigenergy2mqtt/devices/inverter.py
sigenergy2mqtt/devices/inverter_ess.py
sigenergy2mqtt/devices/inverter_pv_string.py
sigenergy2mqtt/devices/plant.py
sigenergy2mqtt/devices/plant_statistics.py
sigenergy2mqtt/devices/smartport/enphase.py
sigenergy2mqtt/main/__init__.py
sigenergy2mqtt/main/main.py
sigenergy2mqtt/main/thread_config.py
sigenergy2mqtt/main/threading.py
sigenergy2mqtt/metrics/metrics.py
sigenergy2mqtt/metrics/metrics_sensors.py
sigenergy2mqtt/metrics/metrics_service.py
sigenergy2mqtt/modbus/__init__.py
sigenergy2mqtt/modbus/client.py
sigenergy2mqtt/modbus/client_factory.py
sigenergy2mqtt/modbus/lock.py
sigenergy2mqtt/modbus/lock_factory.py
sigenergy2mqtt/modbus/read_ahead.py
sigenergy2mqtt/modbus/types.py
sigenergy2mqtt/monitor/__init__.py
sigenergy2mqtt/monitor/monitor_service.py
sigenergy2mqtt/monitor/monitored_sensor.py
sigenergy2mqtt/mqtt/__init__.py
sigenergy2mqtt/mqtt/mqtt.py
sigenergy2mqtt/pvoutput/__init__.py
sigenergy2mqtt/pvoutput/output.py
sigenergy2mqtt/pvoutput/service.py
sigenergy2mqtt/pvoutput/service_topics.py
sigenergy2mqtt/pvoutput/status.py
sigenergy2mqtt/pvoutput/topic.py
sigenergy2mqtt-2026.1.20.dist-info/METADATA
sigenergy2mqtt-2026.1.20.dist-info/WHEEL
sigenergy2mqtt-2026.1.20.dist-info/entry_points.txt
sigenergy2mqtt-2026.1.20.dist-info/licenses/LICENSE
sigenergy2mqtt-2026.1.20.dist-info/RECORD
