Metadata-Version: 2.4
Name: sigenergy2mqtt
Version: 2026.1.20
Summary: Publish Modbus data from Sigenergy to MQTT, with optional Home Assistant Auto-Discovery and PVOutput updating
Project-URL: repository, https://github.com/seud0nym/sigenergy2mqtt
Project-URL: issues, https://github.com/seud0nym/sigenergy2mqtt/issues
Author-email: seud0nym <seud0nym@yahoo.com.au>
License-Expression: MIT
License-File: LICENSE
Requires-Python: >=3.12
Requires-Dist: paho-mqtt==2.1.0
Requires-Dist: psutil==7.2.1
Requires-Dist: pymodbus==3.11.4
Requires-Dist: requests==2.32.5
Requires-Dist: ruamel-yaml==0.19.1
Requires-Dist: scapy==2.7.0
Provides-Extra: test
Requires-Dist: pytest; extra == 'test'
Requires-Dist: pytest-asyncio; extra == 'test'
Requires-Dist: pytest-cov; extra == 'test'
